MANIFEST.in
README
requirements.txt
setup.py
ajenti.plugin.power.egg-info/PKG-INFO
ajenti.plugin.power.egg-info/SOURCES.txt
ajenti.plugin.power.egg-info/dependency_links.txt
ajenti.plugin.power.egg-info/requires.txt
ajenti.plugin.power.egg-info/top_level.txt
ajenti_plugin_power/README.md
ajenti_plugin_power/__init__.py
ajenti_plugin_power/api.py
ajenti_plugin_power/main.py
ajenti_plugin_power/plugin.yml
ajenti_plugin_power/requirements.txt
ajenti_plugin_power/views.py
ajenti_plugin_power/widget.py
ajenti_plugin_power/locale/app.pot
ajenti_plugin_power/locale/af/LC_MESSAGES/app.js
ajenti_plugin_power/locale/af/LC_MESSAGES/app.po
ajenti_plugin_power/locale/af/LC_MESSAGES/app.po~
ajenti_plugin_power/locale/ar/LC_MESSAGES/app.js
ajenti_plugin_power/locale/ar/LC_MESSAGES/app.po
ajenti_plugin_power/locale/ar/LC_MESSAGES/app.po~
ajenti_plugin_power/locale/be/LC_MESSAGES/app.js
ajenti_plugin_power/locale/be/LC_MESSAGES/app.po
ajenti_plugin_power/locale/be/LC_MESSAGES/app.po~
ajenti_plugin_power/locale/bg/LC_MESSAGES/app.js
ajenti_plugin_power/locale/bg/LC_MESSAGES/app.po
ajenti_plugin_power/locale/bg/LC_MESSAGES/app.po~
ajenti_plugin_power/locale/bn/LC_MESSAGES/app.js
ajenti_plugin_power/locale/bn/LC_MESSAGES/app.po
ajenti_plugin_power/locale/bn/LC_MESSAGES/app.po~
ajenti_plugin_power/locale/bs/LC_MESSAGES/app.js
ajenti_plugin_power/locale/bs/LC_MESSAGES/app.po
ajenti_plugin_power/locale/ca/LC_MESSAGES/app.js
ajenti_plugin_power/locale/ca/LC_MESSAGES/app.po
ajenti_plugin_power/locale/ca/LC_MESSAGES/app.po~
ajenti_plugin_power/locale/cs/LC_MESSAGES/app.js
ajenti_plugin_power/locale/cs/LC_MESSAGES/app.po
ajenti_plugin_power/locale/cs/LC_MESSAGES/app.po~
ajenti_plugin_power/locale/da/LC_MESSAGES/app.js
ajenti_plugin_power/locale/da/LC_MESSAGES/app.po
ajenti_plugin_power/locale/da/LC_MESSAGES/app.po~
ajenti_plugin_power/locale/de/LC_MESSAGES/app.js
ajenti_plugin_power/locale/de/LC_MESSAGES/app.po
ajenti_plugin_power/locale/de/LC_MESSAGES/app.po~
ajenti_plugin_power/locale/el/LC_MESSAGES/app.js
ajenti_plugin_power/locale/el/LC_MESSAGES/app.po
ajenti_plugin_power/locale/el/LC_MESSAGES/app.po~
ajenti_plugin_power/locale/en/LC_MESSAGES/app.po
