Metadata-Version: 1.2
Name: ajenti.plugin.power
Version: 0.24
Summary: Power management
Home-page: https://ajenti.org
Author: Ajenti project
Author-email: e@ajenti.org
License: UNKNOWN
Platform: UNKNOWN
Requires-Python: >=3
